pqopen/__init__.py
pqopen/auxcalc.py
pqopen/eventdetector.py
pqopen/helper.py
pqopen/powerquality.py
pqopen/powersystem.py
pqopen/storagecontroller.py
pqopen/zcd.py
pqopen_lib-0.8.5.dist-info/METADATA
pqopen_lib-0.8.5.dist-info/WHEEL
pqopen_lib-0.8.5.dist-info/licenses/LICENSE
pqopen_lib-0.8.5.dist-info/RECORD
