Metadata-Version: 2.4
Name: pqopen-lib
Version: 0.8.5
Summary: A power quality processing library for calculating parameters from waveform data
Project-URL: Homepage, https://github.com/DaqOpen/pqopen-lib
Project-URL: Issues, https://github.com/DaqOpen/pqopen-lib/issues
Author-email: Michael Oberhofer <michael@daqopen.com>
License-File: LICENSE
Classifier: License :: OSI Approved :: MIT License
Classifier: Operating System :: OS Independent
Classifier: Programming Language :: Python :: 3
Requires-Python: >=3.11
Requires-Dist: daqopen-lib>=0.7.4
Requires-Dist: numpy
Requires-Dist: scipy
Provides-Extra: numba
Requires-Dist: numba; extra == 'numba'
